Dockerfile
LICENSE
MANIFEST.in
Makefile
README.md
azure-pipelines.yml
pyzfp.c
pyzfp.pyx
requirements.txt
setup.py
test.py
.eggs/Cython-0.29.26-py3.10-linux-x86_64.egg/Cython/Compiler/Code.pxd
.eggs/Cython-0.29.26-py3.10-linux-x86_64.egg/Cython/Compiler/FlowControl.pxd
.eggs/Cython-0.29.26-py3.10-linux-x86_64.egg/Cython/Compiler/ParseTreeTransforms.pxd
.eggs/Cython-0.29.26-py3.10-linux-x86_64.egg/Cython/Compiler/Parsing.pxd
.eggs/Cython-0.29.26-py3.10-linux-x86_64.egg/Cython/Compiler/Scanning.pxd
.eggs/Cython-0.29.26-py3.10-linux-x86_64.egg/Cython/Compiler/Visitor.pxd
.eggs/Cython-0.29.26-py3.10-linux-x86_64.egg/Cython/Includes/openmp.pxd
.eggs/Cython-0.29.26-py3.10-linux-x86_64.egg/Cython/Includes/Deprecated/python.pxd
.eggs/Cython-0.29.26-py3.10-linux-x86_64.egg/Cython/Includes/Deprecated/python_bool.pxd
.eggs/Cython-0.29.26-py3.10-linux-x86_64.egg/Cython/Includes/Deprecated/python_buffer.pxd
.eggs/Cython-0.29.26-py3.10-linux-x86_64.egg/Cython/Includes/Deprecated/python_bytes.pxd
.eggs/Cython-0.29.26-py3.10-linux-x86_64.egg/Cython/Includes/Deprecated/python_cobject.pxd
.eggs/Cython-0.29.26-py3.10-linux-x86_64.egg/Cython/Includes/Deprecated/python_complex.pxd
.eggs/Cython-0.29.26-py3.10-linux-x86_64.egg/Cython/Includes/Deprecated/python_dict.pxd
.eggs/Cython-0.29.26-py3.10-linux-x86_64.egg/Cython/Includes/Deprecated/python_exc.pxd
.eggs/Cython-0.29.26-py3.10-linux-x86_64.egg/Cython/Includes/Deprecated/python_float.pxd
.eggs/Cython-0.29.26-py3.10-linux-x86_64.egg/Cython/Includes/Deprecated/python_function.pxd
.eggs/Cython-0.29.26-py3.10-linux-x86_64.egg/Cython/Includes/Deprecated/python_getargs.pxd
.eggs/Cython-0.29.26-py3.10-linux-x86_64.egg/Cython/Includes/Deprecated/python_instance.pxd
.eggs/Cython-0.29.26-py3.10-linux-x86_64.egg/Cython/Includes/Deprecated/python_int.pxd
.eggs/Cython-0.29.26-py3.10-linux-x86_64.egg/Cython/Includes/Deprecated/python_iterator.pxd
.eggs/Cython-0.29.26-py3.10-linux-x86_64.egg/Cython/Includes/Deprecated/python_list.pxd
pyzfp.egg-info/PKG-INFO
pyzfp.egg-info/SOURCES.txt
pyzfp.egg-info/dependency_links.txt
pyzfp.egg-info/top_level.txt