Metadata-Version: 2.1
Name: pyzfp
Version: 0.5.5
Summary: A python wrapper for the ZFP compression libary
Home-page: https://github.com/navjotk/pyzfp
Author: Navjot Kukreja
Author-email: navjotk@gmail.com
License: MIT
Platform: UNKNOWN
License-File: LICENSE
